README.rst
setup.py
unleash/__init__.py
unleash/cli.py
unleash/depgraph.py
unleash/exc.py
unleash/git.py
unleash/main.py
unleash/plugin.py
unleash/report.py
unleash/unleash.py
unleash/util.py
unleash.egg-info/PKG-INFO
unleash.egg-info/SOURCES.txt
unleash.egg-info/dependency_links.txt
unleash.egg-info/entry_points.txt
unleash.egg-info/requires.txt
unleash.egg-info/top_level.txt
unleash/plugins/__init__.py
unleash/plugins/docs.py
unleash/plugins/egg_info.py
unleash/plugins/footer.py
unleash/plugins/git.py
unleash/plugins/license.py
unleash/plugins/pypi.py
unleash/plugins/python23.py
unleash/plugins/setupdist.py
unleash/plugins/tox_tests.py
unleash/plugins/travis.py
unleash/plugins/utils_assign.py
unleash/plugins/utils_tree.py
unleash/plugins/versions.py