Metadata-Version: 1.1
Name: unleash
Version: 0.7.1
Summary: Creates release commits directly in git, unleashes them on PyPI and pushes tags to github.
Home-page: http://github.com/mbr/unleash
Author: Marc Brinkmann
Author-email: git@marcbrinkmann.de
License: MIT
Platform: UNKNOWN
Classifier: Programming Language :: Python :: 2
